miteclock/__init__.py
miteclock/activities.py
miteclock/cli.py
miteclock/completions/bash
miteclock/completions/zsh
miteclock/mite.py
miteclock/settings.py
miteclock-23.1.dist-info/LICENSE
miteclock-23.1.dist-info/WHEEL
miteclock-23.1.dist-info/entry_points.txt
miteclock-23.1.dist-info/METADATA
miteclock-23.1.dist-info/RECORD
