Metadata-Version: 2.1
Name: miteclock
Version: 23.1
Summary: Clock in and out of mite.de quickly.
Home-page: https://github.com/iliakur/miteclock
License: MIT
Keywords: time-tracking,productivity
Author: Ilia Kurenkov
Author-email: ilia.kurenkov@gmail.com
Requires-Python: >=3.7,<4.0
Classifier: Development Status :: 5 - Production/Stable
Classifier: Environment :: Console
Classifier: Intended Audience :: Developers
Classifier: Intended Audience :: Information Technology
Classifier: Intended Audience :: System Administrators
Classifier: License :: OSI Approved :: MIT License
Classifier: Operating System :: Unix
Classifier: Programming Language :: Python :: 3
Classifier: Programming Language :: Python :: 3.7
Classifier: Programming Language :: Python :: 3.8
Classifier: Programming Language :: Python :: 3.9
Classifier: Programming Language :: Python :: 3.10
Classifier: Programming Language :: Python :: 3.11
Requires-Dist: attrs (==21.4.0)
Requires-Dist: backoff (==2.2.1)
Requires-Dist: click (==8.1.3)
Requires-Dist: click-aliases (==1.0.1)
Requires-Dist: importlib-metadata (>=4.10.0,<5.0.0) ; python_version == "3.7"
Requires-Dist: requests (==2.28.2)
Requires-Dist: tomlkit (==0.7.2)
Project-URL: Repository, https://github.com/iliakur/miteclock
